bongovaad/__init__.py
bongovaad/__main__.py
bongovaad/transcriber.py
bongovaad-0.5.0.dist-info/LICENSE
bongovaad-0.5.0.dist-info/METADATA
bongovaad-0.5.0.dist-info/WHEEL
bongovaad-0.5.0.dist-info/entry_points.txt
bongovaad-0.5.0.dist-info/top_level.txt
bongovaad-0.5.0.dist-info/RECORD
