Metadata-Version: 2.2
Name: bongovaad
Version: 0.5.0
Summary: Bengali Speech Recognition Tool using Hugging Face Inference API
Home-page: https://github.com/ucalyptus/bongovaad
Author: ucalyptus
Author-email: 
Keywords: bengali,speech recognition,whisper,youtube,transcription,subtitles,huggingface,api
Classifier: Development Status :: 4 - Beta
Classifier: Intended Audience :: Developers
Classifier: Intended Audience :: Science/Research
Classifier: License :: OSI Approved :: MIT License
Classifier: Programming Language :: Python :: 3
Classifier: Programming Language :: Python :: 3.8
Classifier: Programming Language :: Python :: 3.9
Classifier: Programming Language :: Python :: 3.10
Classifier: Topic :: Scientific/Engineering :: Artificial Intelligence
Classifier: Topic :: Multimedia :: Sound/Audio :: Speech
Requires-Python: >=3.8
License-File: LICENSE
Requires-Dist: ffmpeg-python>=0.2.0
Requires-Dist: pydub>=0.25.1
Requires-Dist: pytube>=15.0.0
Requires-Dist: yt-dlp>=2023.3.4
Requires-Dist: tqdm>=4.65.0
Requires-Dist: srt>=3.5.0
Requires-Dist: aiohttp>=3.8.4
Dynamic: author
Dynamic: classifier
Dynamic: description
Dynamic: description-content-type
Dynamic: home-page
Dynamic: keywords
Dynamic: requires-dist
Dynamic: requires-python
Dynamic: summary
